odoo/addons/account_asset_number/README.rst
odoo/addons/account_asset_number/__init__.py
odoo/addons/account_asset_number/__manifest__.py
odoo/addons/account_asset_number/i18n/account_asset_number.pot
odoo/addons/account_asset_number/i18n/es.po
odoo/addons/account_asset_number/i18n/hr.po
odoo/addons/account_asset_number/i18n/pt_BR.po
odoo/addons/account_asset_number/models/__init__.py
odoo/addons/account_asset_number/models/account_asset.py
odoo/addons/account_asset_number/models/account_asset_profile.py
odoo/addons/account_asset_number/readme/CONFIGURE.rst
odoo/addons/account_asset_number/readme/CONTRIBUTORS.rst
odoo/addons/account_asset_number/readme/DESCRIPTION.rst
odoo/addons/account_asset_number/report/__init__.py
odoo/addons/account_asset_number/report/account_asset_number_report.xml
odoo/addons/account_asset_number/report/account_asset_report_xls.py
odoo/addons/account_asset_number/static/description/icon.png
odoo/addons/account_asset_number/static/description/index.html
odoo/addons/account_asset_number/views/account_asset.xml
odoo/addons/account_asset_number/views/account_asset_profile.xml
odoo14_addon_account_asset_number-14.0.1.0.1.dev10.dist-info/METADATA
odoo14_addon_account_asset_number-14.0.1.0.1.dev10.dist-info/WHEEL
odoo14_addon_account_asset_number-14.0.1.0.1.dev10.dist-info/top_level.txt
odoo14_addon_account_asset_number-14.0.1.0.1.dev10.dist-info/RECORD
